{"data":{"propertyOrder":{},"properties":{"id":{"name":"id","reference":"scalar","primary":true,"type":"number"},"flavor":{"name":"flavor","reference":"scalar","getter":false,"setter":false,"type":"Domain.IceCreamFlavor"},"provider":{"name":"provider","reference":"1:m","cascade":["persist"],"type":"IceCream"}},"props":[{"name":"id","reference":"scalar","primary":true,"type":"number"},{"name":"flavor","reference":"scalar","getter":false,"setter":false,"type":"Domain.IceCreamFlavor"},{"name":"provider","reference":"1:m","cascade":["persist"],"type":"IceCream"}],"primaryKeys":["id"],"filters":{},"hooks":{},"indexes":[],"uniques":[],"className":"IceCreamProvider","path":"./src/modules/ice-cream-provider/model.ts","name":"IceCreamProvider","abstract":false,"constructorParams":[],"toJsonParams":[],"extends":"IceCreamProvider","useCache":true,"compositePK":false,"relations":[{"name":"provider","reference":"1:m","cascade":["persist"],"type":"IceCream"}],"collection":"IceCreamProvider"},"origin":"./src/modules/ice-cream-provider/model.ts","hash":"bdee4e0d9e12b64eca38f2e76fcf610e","version":"4.5.5"}
